vtaxa/__init__.py
vtaxa/cli.py
vtaxa/hello.py
vtaxa/vtaxa.py
vtaxa-0.2.1.dist-info/AUTHORS.rst
vtaxa-0.2.1.dist-info/LICENSE
vtaxa-0.2.1.dist-info/METADATA
vtaxa-0.2.1.dist-info/WHEEL
vtaxa-0.2.1.dist-info/entry_points.txt
vtaxa-0.2.1.dist-info/top_level.txt
vtaxa-0.2.1.dist-info/RECORD
